viper/__init__.py
viper/common/__init__.py
viper/common/abstracts.py
viper/common/autorun.py
viper/common/colors.py
viper/common/exceptions.py
viper/common/network.py
viper/common/objects.py
viper/common/out.py
viper/common/utils.py
viper/common/version.py
viper/core/__init__.py
viper/core/archiver.py
viper/core/config.py
viper/core/database.py
viper/core/logger.py
viper/core/plugins.py
viper/core/project.py
viper/core/session.py
viper/core/storage.py
viper/core/ui/__init__.py
viper/core/ui/commands.py
viper/core/ui/console.py
viper/core/ui/main.py
viper/core/ui/cmd/__init__.py
viper/core/ui/cmd/about.py
viper/core/ui/cmd/analysis.py
viper/core/ui/cmd/clear.py
viper/core/ui/cmd/close.py
viper/core/ui/cmd/copy.py
viper/core/ui/cmd/delete.py
viper/core/ui/cmd/export.py
viper/core/ui/cmd/find.py
viper/core/ui/cmd/help.py
viper/core/ui/cmd/info.py
viper/core/ui/cmd/new.py
viper/core/ui/cmd/notes.py
viper/core/ui/cmd/open.py
viper/core/ui/cmd/parent.py
viper/core/ui/cmd/projects.py
viper/core/ui/cmd/rename.py
viper/core/ui/cmd/sessions.py
viper/core/ui/cmd/stats.py
viper/core/ui/cmd/store.py
viper/core/ui/cmd/tags.py
viper/core/ui/cmd/update-modules.py
viper/data/viper.conf.sample
viper/data/peid/UserDB.TXT
viper/data/yara/embedded.yara
viper/data/yara/rats.yara
viper/data/yara/vmdetect.yara
viper_framework-2.0rc11.dist-info/LICENSE
viper_framework-2.0rc11.dist-info/METADATA
viper_framework-2.0rc11.dist-info/WHEEL
viper_framework-2.0rc11.dist-info/entry_points.txt
viper_framework-2.0rc11.dist-info/top_level.txt
viper_framework-2.0rc11.dist-info/RECORD
