Metadata-Version: 2.1
Name: viper-framework
Version: 2.0rc11
Summary: Binary Analysis & Management Framework
Home-page: http://viper.li
Author: Claudio Guarnieri
Author-email: nex@nex.sx
License: BSD 3-Clause
Keywords: binary analysis management malware research
Platform: any
Classifier: Topic :: Security
Classifier: License :: OSI Approved :: BSD License
Classifier: Programming Language :: Python :: 3
Classifier: Programming Language :: Python :: 3.4
Classifier: Programming Language :: Python :: 3.5
Classifier: Programming Language :: Python :: 3.6
Classifier: Programming Language :: Python :: 3.7
Classifier: Operating System :: POSIX :: Linux
Requires-Dist: pydeep (==0.4)
Requires-Dist: python-magic (==0.4.18)
Requires-Dist: rarfile (==3.1)
Requires-Dist: requests-cache (==0.5.2)
Requires-Dist: requests[socks] (==2.24.0)
Requires-Dist: scandir (==1.10)
Requires-Dist: six (==1.15.0)
Requires-Dist: sqlalchemy (==1.3.13)
Requires-Dist: terminaltables (==3.1.0)
